{
  "kind": "collectionType",
  "collectionName": "bookings",
  "info": {
    "singularName": "booking",
    "pluralName": "bookings",
    "displayName": "Booking",
    "description": ""
  },
  "options": {
    "draftAndPublish": false
  },
  "pluginOptions": {},
  "attributes": {
    "userName": {
      "type": "string"
    },
    "artistName": {
      "type": "string"
    },
    "message": {
      "type": "string"
    },
    "phone": {
      "type": "string"
    },
    "email": {
      "type": "string"
    },
    "date": {
      "type": "datetime"
    }
  }
}
